pyvltree/__init__.py
pyvltree/_avl_node.py
pyvltree/avl_tree.py
pyvltree-0.5.1.dist-info/LICENSE.txt
pyvltree-0.5.1.dist-info/METADATA
pyvltree-0.5.1.dist-info/WHEEL
pyvltree-0.5.1.dist-info/top_level.txt
pyvltree-0.5.1.dist-info/RECORD
